{
  "device": "openaps://indy-e1", 
  "pump": {
    "battery": {
      "status": "normal", 
      "voltage": 1.46
    }, 
    "status": {
      "status": "normal", 
      "timestamp": "2016-07-24T21:58:06.000Z", 
      "bolusing": false, 
      "suspended": false
    }, 
    "reservoir": 93.725, 
    "clock": "2016-07-24T14:57:49-07:00"
  }, 
  "uploader": {
    "battery": 73, 
    "batteryVoltage": 3906
  }, 
  "openaps": {
    "suggested": {
      "bg": 182, 
      "temp": "absolute", 
      "snoozeBG": 146, 
      "timestamp": "2016-07-24T21:59:18.000Z", 
      "predBGs": {
        "COB": [
          182, 
          186, 
          190, 
          193, 
          196, 
          197, 
          198, 
          199, 
          198, 
          197, 
          195, 
          192, 
          188, 
          184, 
          180, 
          175, 
          170, 
          165, 
          161, 
          157, 
          153, 
          149, 
          146, 
          142, 
          139, 
          137, 
          134, 
          132, 
          130, 
          129, 
          127, 
          126, 
          126, 
          125, 
          124
        ], 
        "aCOB": [
          182, 
          186, 
          190, 
          193, 
          195, 
          197, 
          198, 
          198, 
          198, 
          196, 
          194, 
          192, 
          188, 
          184, 
          180, 
          175, 
          170, 
          165, 
          161, 
          157, 
          153, 
          149, 
          146, 
          142, 
          139, 
          137, 
          134, 
          132, 
          130, 
          129, 
          127, 
          126, 
          126, 
          125, 
          124
        ], 
        "IOB": [
          182, 
          186, 
          190, 
          192, 
          194, 
          195, 
          195, 
          194, 
          192, 
          189, 
          186, 
          181, 
          176, 
          170, 
          165, 
          160, 
          155, 
          151, 
          146, 
          142, 
          138, 
          135, 
          131, 
          128, 
          125, 
          122, 
          120, 
          118, 
          116, 
          114, 
          113, 
          112, 
          111, 
          111, 
          110, 
          110, 
          109
        ]
      }, 
      "rate": 2.3, 
      "reason": "COB: 15, Dev: 60, BGI: -5.08, ISF: 80, Target: 80; Eventual BG 146 >= 80, temp 1.425<2.3U/hr", 
      "COB": 15, 
      "eventualBG": 146, 
      "duration": 30, 
      "tick": "+5", 
      "IOB": 1.194
    }, 
    "iob": [
      {
        "netbasalinsulin": 1.9, 
        "activity": 0.0127, 
        "basaliob": 0.94, 
        "time": "2016-07-24T21:57:49.000Z", 
        "hightempinsulin": 2.2, 
        "bolussnooze": 0, 
        "iob": 1.194
      }, 
      {
        "netbasalinsulin": 2, 
        "activity": 0.0125, 
        "basaliob": 1.006, 
        "time": "2016-07-24T22:02:49.000Z", 
        "hightempinsulin": 2.25, 
        "bolussnooze": 0, 
        "iob": 1.231
      }, 
      {
        "netbasalinsulin": 2.05, 
        "activity": 0.0124, 
        "basaliob": 1.022, 
        "time": "2016-07-24T22:07:49.000Z", 
        "hightempinsulin": 2.3, 
        "bolussnooze": 0, 
        "iob": 1.22
      }, 
      {
        "netbasalinsulin": 2.1, 
        "activity": 0.0124, 
        "basaliob": 1.035, 
        "time": "2016-07-24T22:12:49.000Z", 
        "hightempinsulin": 2.35, 
        "bolussnooze": 0, 
        "iob": 1.208
      }, 
      {
        "netbasalinsulin": 2.15, 
        "activity": 0.0124, 
        "basaliob": 1.097, 
        "time": "2016-07-24T22:17:49.000Z", 
        "hightempinsulin": 2.4, 
        "bolussnooze": 0, 
        "iob": 1.246
      }, 
      {
        "netbasalinsulin": 2.2, 
        "activity": 0.0126, 
        "basaliob": 1.106, 
        "time": "2016-07-24T22:22:49.000Z", 
        "hightempinsulin": 2.45, 
        "bolussnooze": 0, 
        "iob": 1.233
      }, 
      {
        "netbasalinsulin": 2.15, 
        "activity": 0.0128, 
        "basaliob": 1.062, 
        "time": "2016-07-24T22:27:49.000Z", 
        "hightempinsulin": 2.4, 
        "bolussnooze": 0, 
        "iob": 1.169
      }, 
      {
        "netbasalinsulin": 2.1, 
        "activity": 0.0131, 
        "basaliob": 1.015, 
        "time": "2016-07-24T22:32:49.000Z", 
        "hightempinsulin": 2.35, 
        "bolussnooze": 0, 
        "iob": 1.104
      }, 
      {
        "netbasalinsulin": 1.95, 
        "activity": 0.0133, 
        "basaliob": 0.965, 
        "time": "2016-07-24T22:37:49.000Z", 
        "hightempinsulin": 2.2, 
        "bolussnooze": 0, 
        "iob": 1.037
      }, 
      {
        "netbasalinsulin": 1.8, 
        "activity": 0.0134, 
        "basaliob": 0.913, 
        "time": "2016-07-24T22:42:49.000Z", 
        "hightempinsulin": 2.05, 
        "bolussnooze": 0, 
        "iob": 0.97
      }, 
      {
        "netbasalinsulin": 1.65, 
        "activity": 0.0134, 
        "basaliob": 0.859, 
        "time": "2016-07-24T22:47:49.000Z", 
        "hightempinsulin": 1.9, 
        "bolussnooze": 0, 
        "iob": 0.903
      }, 
      {
        "netbasalinsulin": 1.5, 
        "activity": 0.0134, 
        "basaliob": 0.803, 
        "time": "2016-07-24T22:52:49.000Z", 
        "hightempinsulin": 1.75, 
        "bolussnooze": 0, 
        "iob": 0.836
      }, 
      {
        "netbasalinsulin": 1.35, 
        "activity": 0.0133, 
        "basaliob": 0.747, 
        "time": "2016-07-24T22:57:49.000Z", 
        "hightempinsulin": 1.6, 
        "bolussnooze": 0, 
        "iob": 0.77
      }, 
      {
        "netbasalinsulin": 1.25, 
        "activity": 0.013, 
        "basaliob": 0.69, 
        "time": "2016-07-24T23:02:49.000Z", 
        "hightempinsulin": 1.5, 
        "bolussnooze": 0, 
        "iob": 0.705
      }, 
      {
        "netbasalinsulin": 1.15, 
        "activity": 0.0126, 
        "basaliob": 0.633, 
        "time": "2016-07-24T23:07:49.000Z", 
        "hightempinsulin": 1.4, 
        "bolussnooze": 0, 
        "iob": 0.641
      }, 
      {
        "netbasalinsulin": 1.15, 
        "activity": 0.0121, 
        "basaliob": 0.577, 
        "time": "2016-07-24T23:12:49.000Z", 
        "hightempinsulin": 1.4, 
        "bolussnooze": 0, 
        "iob": 0.581
      }, 
      {
        "netbasalinsulin": 1.1, 
        "activity": 0.0116, 
        "basaliob": 0.522, 
        "time": "2016-07-24T23:17:49.000Z", 
        "hightempinsulin": 1.35, 
        "bolussnooze": 0, 
        "iob": 0.523
      }, 
      {
        "netbasalinsulin": 1.1, 
        "activity": 0.0109, 
        "basaliob": 0.468, 
        "time": "2016-07-24T23:22:49.000Z", 
        "hightempinsulin": 1.35, 
        "bolussnooze": 0, 
        "iob": 0.468
      }, 
      {
        "netbasalinsulin": 1.1, 
        "activity": 0.0103, 
        "basaliob": 0.416, 
        "time": "2016-07-24T23:27:49.000Z", 
        "hightempinsulin": 1.35, 
        "bolussnooze": 0, 
        "iob": 0.416
      }, 
      {
        "netbasalinsulin": 1.1, 
        "activity": 0.0099, 
        "basaliob": 0.367, 
        "time": "2016-07-24T23:32:49.000Z", 
        "hightempinsulin": 1.35, 
        "bolussnooze": 0, 
        "iob": 0.367
      }, 
      {
        "netbasalinsulin": 1.15, 
        "activity": 0.0093, 
        "basaliob": 0.32, 
        "time": "2016-07-24T23:37:49.000Z", 
        "hightempinsulin": 1.35, 
        "bolussnooze": 0, 
        "iob": 0.32
      }, 
      {
        "netbasalinsulin": 1.2, 
        "activity": 0.0087, 
        "basaliob": 0.277, 
        "time": "2016-07-24T23:42:49.000Z", 
        "hightempinsulin": 1.35, 
        "bolussnooze": 0, 
        "iob": 0.277
      }, 
      {
        "netbasalinsulin": 1.25, 
        "activity": 0.0081, 
        "basaliob": 0.236, 
        "time": "2016-07-24T23:47:49.000Z", 
        "hightempinsulin": 1.35, 
        "bolussnooze": 0, 
        "iob": 0.236
      }, 
      {
        "netbasalinsulin": 1.3, 
        "activity": 0.0074, 
        "basaliob": 0.199, 
        "time": "2016-07-24T23:52:49.000Z", 
        "hightempinsulin": 1.35, 
        "bolussnooze": 0, 
        "iob": 0.199
      }, 
      {
        "netbasalinsulin": 1.3, 
        "activity": 0.0067, 
        "basaliob": 0.166, 
        "time": "2016-07-24T23:57:49.000Z", 
        "hightempinsulin": 1.35, 
        "bolussnooze": 0, 
        "iob": 0.166
      }, 
      {
        "netbasalinsulin": 1.3, 
        "activity": 0.006, 
        "basaliob": 0.135, 
        "time": "2016-07-25T00:02:49.000Z", 
        "hightempinsulin": 1.35, 
        "bolussnooze": 0, 
        "iob": 0.135
      }, 
      {
        "netbasalinsulin": 1.35, 
        "activity": 0.0053, 
        "basaliob": 0.109, 
        "time": "2016-07-25T00:07:49.000Z", 
        "hightempinsulin": 1.35, 
        "bolussnooze": 0, 
        "iob": 0.109
      }, 
      {
        "netbasalinsulin": 1.35, 
        "activity": 0.0046, 
        "basaliob": 0.086, 
        "time": "2016-07-25T00:12:49.000Z", 
        "hightempinsulin": 1.35, 
        "bolussnooze": 0, 
        "iob": 0.086
      }, 
      {
        "netbasalinsulin": 1.35, 
        "activity": 0.0039, 
        "basaliob": 0.066, 
        "time": "2016-07-25T00:17:49.000Z", 
        "hightempinsulin": 1.35, 
        "bolussnooze": 0, 
        "iob": 0.066
      }, 
      {
        "netbasalinsulin": 1.2, 
        "activity": 0.0032, 
        "basaliob": 0.05, 
        "time": "2016-07-25T00:22:49.000Z", 
        "hightempinsulin": 1.2, 
        "bolussnooze": 0, 
        "iob": 0.05
      }, 
      {
        "netbasalinsulin": 1.1, 
        "activity": 0.0026, 
        "basaliob": 0.037, 
        "time": "2016-07-25T00:27:49.000Z", 
        "hightempinsulin": 1.1, 
        "bolussnooze": 0, 
        "iob": 0.037
      }, 
      {
        "netbasalinsulin": 1, 
        "activity": 0.0021, 
        "basaliob": 0.026, 
        "time": "2016-07-25T00:32:49.000Z", 
        "hightempinsulin": 1, 
        "bolussnooze": 0, 
        "iob": 0.026
      }, 
      {
        "netbasalinsulin": 0.85, 
        "activity": 0.0016, 
        "basaliob": 0.018, 
        "time": "2016-07-25T00:37:49.000Z", 
        "hightempinsulin": 0.85, 
        "bolussnooze": 0, 
        "iob": 0.018
      }, 
      {
        "netbasalinsulin": 0.7, 
        "activity": 0.0012, 
        "basaliob": 0.012, 
        "time": "2016-07-25T00:42:49.000Z", 
        "hightempinsulin": 0.7, 
        "bolussnooze": 0, 
        "iob": 0.012
      }, 
      {
        "netbasalinsulin": 0.55, 
        "activity": 0.0009, 
        "basaliob": 0.008, 
        "time": "2016-07-25T00:47:49.000Z", 
        "hightempinsulin": 0.55, 
        "bolussnooze": 0, 
        "iob": 0.008
      }, 
      {
        "netbasalinsulin": 0.4, 
        "activity": 0.0006, 
        "basaliob": 0.005, 
        "time": "2016-07-25T00:52:49.000Z", 
        "hightempinsulin": 0.4, 
        "bolussnooze": 0, 
        "iob": 0.005
      }
    ], 
    "enacted": {
      "bg": 182, 
      "temp": "absolute", 
      "snoozeBG": 146, 
      "recieved": true, 
      "predBGs": {
        "COB": [
          182, 
          186, 
          190, 
          193, 
          196, 
          197, 
          198, 
          199, 
          198, 
          197, 
          195, 
          192, 
          188, 
          184, 
          180, 
          175, 
          170, 
          165, 
          161, 
          157, 
          153, 
          149, 
          146, 
          142, 
          139, 
          137, 
          134, 
          132, 
          130, 
          129, 
          127, 
          126, 
          126, 
          125, 
          124
        ], 
        "aCOB": [
          182, 
          186, 
          190, 
          193, 
          195, 
          197, 
          198, 
          198, 
          198, 
          196, 
          194, 
          192, 
          188, 
          184, 
          180, 
          175, 
          170, 
          165, 
          161, 
          157, 
          153, 
          149, 
          146, 
          142, 
          139, 
          137, 
          134, 
          132, 
          130, 
          129, 
          127, 
          126, 
          126, 
          125, 
          124
        ], 
        "IOB": [
          182, 
          186, 
          190, 
          192, 
          194, 
          195, 
          195, 
          194, 
          192, 
          189, 
          186, 
          181, 
          176, 
          170, 
          165, 
          160, 
          155, 
          151, 
          146, 
          142, 
          138, 
          135, 
          131, 
          128, 
          125, 
          122, 
          120, 
          118, 
          116, 
          114, 
          113, 
          112, 
          111, 
          111, 
          110, 
          110, 
          109
        ]
      }, 
      "reason": "COB: 15, Dev: 60, BGI: -5.08, ISF: 80, Target: 80; Eventual BG 146 >= 80, temp 1.425<2.3U/hr", 
      "rate": 2.275, 
      "COB": 15, 
      "eventualBG": 146, 
      "timestamp": "2016-07-24T21:59:30.000Z", 
      "duration": 30, 
      "tick": "+5", 
      "IOB": 1.194
    }
  }, 
  "mmtune": {
    "scanDetails": [
      [
        "916.564", 
        5, 
        -67
      ], 
      [
        "916.588", 
        5, 
        -58
      ], 
      [
        "916.612", 
        5, 
        -58
      ], 
      [
        "916.636", 
        5, 
        -63
      ], 
      [
        "916.660", 
        5, 
        -65
      ], 
      [
        "916.684", 
        5, 
        -59
      ], 
      [
        "916.708", 
        5, 
        -67
      ]
    ], 
    "setFreq": 916.612, 
    "timestamp": "2016-07-24T21:57:44.000Z", 
    "usedDefault": false
  }
}