{
  "device": "openaps://indy-e1", 
  "pump": {
    "battery": {
      "status": "normal", 
      "voltage": 1.46
    }, 
    "status": {
      "status": "normal", 
      "timestamp": "2016-07-24T21:16:44.000Z", 
      "bolusing": false, 
      "suspended": false
    }, 
    "reservoir": 95.175, 
    "clock": "2016-07-24T14:16:28-07:00"
  }, 
  "uploader": {
    "battery": 77, 
    "batteryVoltage": 3945
  }, 
  "openaps": {
    "suggested": {
      "bg": 140, 
      "temp": "absolute", 
      "snoozeBG": 154, 
      "timestamp": "2016-07-24T21:18:04.000Z", 
      "predBGs": {
        "COB": [
          140, 
          142, 
          144, 
          145, 
          147, 
          148, 
          149, 
          151, 
          152, 
          154, 
          156, 
          157, 
          159, 
          162, 
          164, 
          166, 
          168, 
          170, 
          173, 
          175, 
          177, 
          179, 
          181, 
          183, 
          184, 
          186, 
          187, 
          188, 
          189
        ], 
        "aCOB": [
          140, 
          144, 
          147, 
          150, 
          153, 
          156, 
          158, 
          160, 
          163, 
          165, 
          167, 
          170, 
          172, 
          174, 
          176, 
          178, 
          180, 
          181, 
          183, 
          184, 
          186, 
          186, 
          187, 
          187, 
          187, 
          187, 
          188
        ], 
        "IOB": [
          140, 
          142, 
          143, 
          143, 
          143, 
          142, 
          141, 
          139, 
          138, 
          136, 
          134, 
          131, 
          128, 
          126, 
          124, 
          122, 
          120, 
          119, 
          118, 
          118, 
          117, 
          117, 
          116, 
          116, 
          116, 
          116, 
          117
        ]
      }, 
      "rate": 2.5, 
      "reason": "COB: 24, Dev: 48, BGI: -5.76, ISF: 80, Target: 80; Eventual BG 189 >= 80, temp 0.675<2.5U/hr", 
      "COB": 24, 
      "eventualBG": 189, 
      "duration": 30, 
      "tick": "+5", 
      "IOB": 0.763
    }, 
    "iob": [
      {
        "netbasalinsulin": 0.85, 
        "activity": 0.0144, 
        "basaliob": 0.247, 
        "time": "2016-07-24T21:16:28.000Z", 
        "hightempinsulin": 1.25, 
        "bolussnooze": 0.204, 
        "iob": 0.763
      }, 
      {
        "netbasalinsulin": 0.85, 
        "activity": 0.0142, 
        "basaliob": 0.202, 
        "time": "2016-07-24T21:21:28.000Z", 
        "hightempinsulin": 1.25, 
        "bolussnooze": 0.154, 
        "iob": 0.692
      }, 
      {
        "netbasalinsulin": 0.85, 
        "activity": 0.014, 
        "basaliob": 0.161, 
        "time": "2016-07-24T21:26:28.000Z", 
        "hightempinsulin": 1.25, 
        "bolussnooze": 0.112, 
        "iob": 0.622
      }, 
      {
        "netbasalinsulin": 0.85, 
        "activity": 0.0138, 
        "basaliob": 0.124, 
        "time": "2016-07-24T21:31:28.000Z", 
        "hightempinsulin": 1.25, 
        "bolussnooze": 0.076, 
        "iob": 0.553
      }, 
      {
        "netbasalinsulin": 0.9, 
        "activity": 0.0135, 
        "basaliob": 0.09, 
        "time": "2016-07-24T21:36:28.000Z", 
        "hightempinsulin": 1.25, 
        "bolussnooze": 0.047, 
        "iob": 0.486
      }, 
      {
        "netbasalinsulin": 0.9, 
        "activity": 0.0131, 
        "basaliob": 0.06, 
        "time": "2016-07-24T21:41:28.000Z", 
        "hightempinsulin": 1.25, 
        "bolussnooze": 0.025, 
        "iob": 0.42
      }, 
      {
        "netbasalinsulin": 0.9, 
        "activity": 0.012, 
        "basaliob": 0.035, 
        "time": "2016-07-24T21:46:28.000Z", 
        "hightempinsulin": 1.25, 
        "bolussnooze": 0.01, 
        "iob": 0.36
      }, 
      {
        "netbasalinsulin": 0.85, 
        "activity": 0.0109, 
        "basaliob": 0.013, 
        "time": "2016-07-24T21:51:28.000Z", 
        "hightempinsulin": 1.2, 
        "bolussnooze": 0.002, 
        "iob": 0.306
      }, 
      {
        "netbasalinsulin": 0.9, 
        "activity": 0.0098, 
        "basaliob": -0.005, 
        "time": "2016-07-24T21:56:28.000Z", 
        "hightempinsulin": 1.2, 
        "bolussnooze": 0, 
        "iob": 0.257
      }, 
      {
        "netbasalinsulin": 0.95, 
        "activity": 0.0088, 
        "basaliob": -0.02, 
        "time": "2016-07-24T22:01:28.000Z", 
        "hightempinsulin": 1.2, 
        "bolussnooze": 0, 
        "iob": 0.213
      }, 
      {
        "netbasalinsulin": 0.9, 
        "activity": 0.0078, 
        "basaliob": -0.032, 
        "time": "2016-07-24T22:06:28.000Z", 
        "hightempinsulin": 1.15, 
        "bolussnooze": 0, 
        "iob": 0.173
      }, 
      {
        "netbasalinsulin": 0.9, 
        "activity": 0.007, 
        "basaliob": -0.041, 
        "time": "2016-07-24T22:11:28.000Z", 
        "hightempinsulin": 1.15, 
        "bolussnooze": 0, 
        "iob": 0.139
      }, 
      {
        "netbasalinsulin": 0.85, 
        "activity": 0.0061, 
        "basaliob": -0.047, 
        "time": "2016-07-24T22:16:28.000Z", 
        "hightempinsulin": 1.1, 
        "bolussnooze": 0, 
        "iob": 0.108
      }, 
      {
        "netbasalinsulin": 0.85, 
        "activity": 0.0053, 
        "basaliob": -0.051, 
        "time": "2016-07-24T22:21:28.000Z", 
        "hightempinsulin": 1.1, 
        "bolussnooze": 0, 
        "iob": 0.082
      }, 
      {
        "netbasalinsulin": 0.8, 
        "activity": 0.0045, 
        "basaliob": -0.053, 
        "time": "2016-07-24T22:26:28.000Z", 
        "hightempinsulin": 1.05, 
        "bolussnooze": 0, 
        "iob": 0.06
      }, 
      {
        "netbasalinsulin": 0.75, 
        "activity": 0.0037, 
        "basaliob": -0.053, 
        "time": "2016-07-24T22:31:28.000Z", 
        "hightempinsulin": 1, 
        "bolussnooze": 0, 
        "iob": 0.041
      }, 
      {
        "netbasalinsulin": 0.6, 
        "activity": 0.003, 
        "basaliob": -0.051, 
        "time": "2016-07-24T22:36:28.000Z", 
        "hightempinsulin": 0.85, 
        "bolussnooze": 0, 
        "iob": 0.026
      }, 
      {
        "netbasalinsulin": 0.5, 
        "activity": 0.0024, 
        "basaliob": -0.047, 
        "time": "2016-07-24T22:41:28.000Z", 
        "hightempinsulin": 0.75, 
        "bolussnooze": 0, 
        "iob": 0.014
      }, 
      {
        "netbasalinsulin": 0.35, 
        "activity": 0.0018, 
        "basaliob": -0.043, 
        "time": "2016-07-24T22:46:28.000Z", 
        "hightempinsulin": 0.6, 
        "bolussnooze": 0, 
        "iob": 0.005
      }, 
      {
        "netbasalinsulin": 0.2, 
        "activity": 0.0013, 
        "basaliob": -0.038, 
        "time": "2016-07-24T22:51:28.000Z", 
        "hightempinsulin": 0.45, 
        "bolussnooze": 0, 
        "iob": -0.002
      }, 
      {
        "netbasalinsulin": 0.05, 
        "activity": 0.0009, 
        "basaliob": -0.032, 
        "time": "2016-07-24T22:56:28.000Z", 
        "hightempinsulin": 0.3, 
        "bolussnooze": 0, 
        "iob": -0.006
      }, 
      {
        "netbasalinsulin": -0.1, 
        "activity": 0.0006, 
        "basaliob": -0.026, 
        "time": "2016-07-24T23:01:28.000Z", 
        "hightempinsulin": 0.15, 
        "bolussnooze": 0, 
        "iob": -0.009
      }, 
      {
        "netbasalinsulin": -0.15, 
        "activity": 0.0003, 
        "basaliob": -0.021, 
        "time": "2016-07-24T23:06:28.000Z", 
        "hightempinsulin": 0.1, 
        "bolussnooze": 0, 
        "iob": -0.011
      }, 
      {
        "netbasalinsulin": -0.2, 
        "activity": 0.0001, 
        "basaliob": -0.016, 
        "time": "2016-07-24T23:11:28.000Z", 
        "hightempinsulin": 0.05, 
        "bolussnooze": 0, 
        "iob": -0.011
      }, 
      {
        "netbasalinsulin": -0.25, 
        "activity": -0.0002, 
        "basaliob": -0.012, 
        "time": "2016-07-24T23:16:28.000Z", 
        "hightempinsulin": 0, 
        "bolussnooze": 0, 
        "iob": -0.011
      }, 
      {
        "netbasalinsulin": -0.25, 
        "activity": -0.0004, 
        "basaliob": -0.009, 
        "time": "2016-07-24T23:21:28.000Z", 
        "hightempinsulin": 0, 
        "bolussnooze": 0, 
        "iob": -0.009
      }, 
      {
        "netbasalinsulin": -0.25, 
        "activity": -0.0006, 
        "basaliob": -0.006, 
        "time": "2016-07-24T23:26:28.000Z", 
        "hightempinsulin": 0, 
        "bolussnooze": 0, 
        "iob": -0.006
      }, 
      {
        "netbasalinsulin": -0.25, 
        "activity": -0.0004, 
        "basaliob": -0.004, 
        "time": "2016-07-24T23:31:28.000Z", 
        "hightempinsulin": 0, 
        "bolussnooze": 0, 
        "iob": -0.004
      }, 
      {
        "netbasalinsulin": -0.25, 
        "activity": -0.0003, 
        "basaliob": -0.002, 
        "time": "2016-07-24T23:36:28.000Z", 
        "hightempinsulin": 0, 
        "bolussnooze": 0, 
        "iob": -0.002
      }, 
      {
        "netbasalinsulin": -0.2, 
        "activity": -0.0002, 
        "basaliob": -0.001, 
        "time": "2016-07-24T23:41:28.000Z", 
        "hightempinsulin": 0, 
        "bolussnooze": 0, 
        "iob": -0.001
      }, 
      {
        "netbasalinsulin": -0.15, 
        "activity": -0.0001, 
        "basaliob": -0.001, 
        "time": "2016-07-24T23:46:28.000Z", 
        "hightempinsulin": 0, 
        "bolussnooze": 0, 
        "iob": -0.001
      }, 
      {
        "netbasalinsulin": -0.1, 
        "activity": -0.0001, 
        "basaliob": 0, 
        "time": "2016-07-24T23:51:28.000Z", 
        "hightempinsulin": 0, 
        "bolussnooze": 0, 
        "iob": 0
      }, 
      {
        "netbasalinsulin": -0.05, 
        "activity": 0, 
        "basaliob": 0, 
        "time": "2016-07-24T23:56:28.000Z", 
        "hightempinsulin": 0, 
        "bolussnooze": 0, 
        "iob": 0
      }, 
      {
        "netbasalinsulin": -0.05, 
        "activity": 0, 
        "basaliob": 0, 
        "time": "2016-07-25T00:01:28.000Z", 
        "hightempinsulin": 0, 
        "bolussnooze": 0, 
        "iob": 0
      }, 
      {
        "netbasalinsulin": 0, 
        "activity": 0, 
        "basaliob": 0, 
        "time": "2016-07-25T00:06:28.000Z", 
        "hightempinsulin": 0, 
        "bolussnooze": 0, 
        "iob": 0
      }, 
      {
        "netbasalinsulin": 0, 
        "activity": 0, 
        "basaliob": 0, 
        "time": "2016-07-25T00:11:28.000Z", 
        "hightempinsulin": 0, 
        "bolussnooze": 0, 
        "iob": 0
      }
    ], 
    "enacted": {
      "bg": 140, 
      "temp": "absolute", 
      "snoozeBG": 154, 
      "recieved": true, 
      "predBGs": {
        "COB": [
          140, 
          142, 
          144, 
          145, 
          147, 
          148, 
          149, 
          151, 
          152, 
          154, 
          156, 
          157, 
          159, 
          162, 
          164, 
          166, 
          168, 
          170, 
          173, 
          175, 
          177, 
          179, 
          181, 
          183, 
          184, 
          186, 
          187, 
          188, 
          189
        ], 
        "aCOB": [
          140, 
          144, 
          147, 
          150, 
          153, 
          156, 
          158, 
          160, 
          163, 
          165, 
          167, 
          170, 
          172, 
          174, 
          176, 
          178, 
          180, 
          181, 
          183, 
          184, 
          186, 
          186, 
          187, 
          187, 
          187, 
          187, 
          188
        ], 
        "IOB": [
          140, 
          142, 
          143, 
          143, 
          143, 
          142, 
          141, 
          139, 
          138, 
          136, 
          134, 
          131, 
          128, 
          126, 
          124, 
          122, 
          120, 
          119, 
          118, 
          118, 
          117, 
          117, 
          116, 
          116, 
          116, 
          116, 
          117
        ]
      }, 
      "reason": "COB: 24, Dev: 48, BGI: -5.76, ISF: 80, Target: 80; Eventual BG 189 >= 80, temp 0.675<2.5U/hr", 
      "rate": 2.5, 
      "COB": 24, 
      "eventualBG": 189, 
      "timestamp": "2016-07-24T21:18:16.000Z", 
      "duration": 30, 
      "tick": "+5", 
      "IOB": 0.763
    }
  }, 
  "mmtune": {
    "scanDetails": [
      [
        "916.564", 
        5, 
        -62
      ], 
      [
        "916.588", 
        5, 
        -59
      ], 
      [
        "916.612", 
        5, 
        -58
      ], 
      [
        "916.636", 
        4, 
        -67
      ], 
      [
        "916.660", 
        5, 
        -60
      ], 
      [
        "916.684", 
        5, 
        -61
      ], 
      [
        "916.708", 
        5, 
        -73
      ]
    ], 
    "setFreq": 916.612, 
    "timestamp": "2016-07-24T21:16:20.000Z", 
    "usedDefault": false
  }
}