{
  "device": "openaps://indy-e1", 
  "pump": {
    "battery": {
      "status": "normal", 
      "voltage": 1.54
    }, 
    "status": {
      "status": "normal", 
      "timestamp": "2016-07-24T05:48:26.000Z", 
      "bolusing": false, 
      "suspended": false
    }, 
    "reservoir": 106.1, 
    "clock": "2016-07-23T22:47:45-07:00"
  }, 
  "uploader": {
    "battery": 100, 
    "batteryVoltage": 4374
  }, 
  "openaps": {
    "suggested": {
      "bg": 143, 
      "temp": "absolute", 
      "snoozeBG": 148, 
      "timestamp": "2016-07-24T05:50:09.000Z", 
      "predBGs": {
        "COB": [
          143, 
          146, 
          149, 
          151, 
          154, 
          155, 
          157, 
          157, 
          158, 
          158, 
          157, 
          156, 
          155, 
          154, 
          153, 
          152, 
          151, 
          150, 
          149, 
          148, 
          148, 
          148, 
          148, 
          148, 
          148, 
          149, 
          150, 
          151, 
          153, 
          154, 
          156, 
          158, 
          160, 
          162, 
          164, 
          167, 
          169
        ], 
        "aCOB": [
          143, 
          150, 
          157, 
          164, 
          170, 
          176, 
          180, 
          184, 
          187, 
          190, 
          192, 
          194, 
          195, 
          196, 
          196, 
          196, 
          197, 
          197, 
          196, 
          196, 
          196, 
          196, 
          196, 
          196, 
          196, 
          197, 
          197, 
          197, 
          197, 
          197, 
          197, 
          197, 
          197, 
          196
        ], 
        "IOB": [
          143, 
          146, 
          148, 
          149, 
          150, 
          150, 
          149, 
          147, 
          145, 
          141, 
          137, 
          133, 
          128, 
          122, 
          117, 
          112, 
          106, 
          102, 
          97, 
          93, 
          89, 
          85, 
          81, 
          78, 
          76, 
          73, 
          71, 
          69, 
          68, 
          67, 
          66, 
          65, 
          64, 
          64, 
          63
        ]
      }, 
      "rate": 2.3, 
      "reason": "COB: 30, Dev: 32, BGI: -2.31, ISF: 88.9, Target: 80; Eventual BG 169 >= 80, temp 2.525<2.3U/hr", 
      "COB": 30, 
      "eventualBG": 169, 
      "duration": 30, 
      "tick": "+3", 
      "IOB": 1.049
    }, 
    "iob": [
      {
        "netbasalinsulin": 0.9, 
        "activity": 0.0052, 
        "basaliob": 1.036, 
        "time": "2016-07-24T05:47:45.000Z", 
        "hightempinsulin": 1.4, 
        "bolussnooze": 0, 
        "iob": 1.049
      }, 
      {
        "netbasalinsulin": 1.05, 
        "activity": 0.0053, 
        "basaliob": 1.17, 
        "time": "2016-07-24T05:52:45.000Z", 
        "hightempinsulin": 1.55, 
        "bolussnooze": 0, 
        "iob": 1.173
      }, 
      {
        "netbasalinsulin": 1.05, 
        "activity": 0.0054, 
        "basaliob": 1.147, 
        "time": "2016-07-24T05:57:45.000Z", 
        "hightempinsulin": 1.55, 
        "bolussnooze": 0, 
        "iob": 1.146
      }, 
      {
        "netbasalinsulin": 1.1, 
        "activity": 0.0059, 
        "basaliob": 1.117, 
        "time": "2016-07-24T06:02:45.000Z", 
        "hightempinsulin": 1.55, 
        "bolussnooze": 0, 
        "iob": 1.117
      }, 
      {
        "netbasalinsulin": 1.1, 
        "activity": 0.0071, 
        "basaliob": 1.082, 
        "time": "2016-07-24T06:07:45.000Z", 
        "hightempinsulin": 1.55, 
        "bolussnooze": 0, 
        "iob": 1.082
      }, 
      {
        "netbasalinsulin": 1.1, 
        "activity": 0.0081, 
        "basaliob": 1.041, 
        "time": "2016-07-24T06:12:45.000Z", 
        "hightempinsulin": 1.55, 
        "bolussnooze": 0, 
        "iob": 1.041
      }, 
      {
        "netbasalinsulin": 1.15, 
        "activity": 0.009, 
        "basaliob": 0.996, 
        "time": "2016-07-24T06:17:45.000Z", 
        "hightempinsulin": 1.55, 
        "bolussnooze": 0, 
        "iob": 0.996
      }, 
      {
        "netbasalinsulin": 1.15, 
        "activity": 0.0097, 
        "basaliob": 0.947, 
        "time": "2016-07-24T06:22:45.000Z", 
        "hightempinsulin": 1.55, 
        "bolussnooze": 0, 
        "iob": 0.947
      }, 
      {
        "netbasalinsulin": 1.15, 
        "activity": 0.0104, 
        "basaliob": 0.895, 
        "time": "2016-07-24T06:27:45.000Z", 
        "hightempinsulin": 1.55, 
        "bolussnooze": 0, 
        "iob": 0.895
      }, 
      {
        "netbasalinsulin": 1.15, 
        "activity": 0.011, 
        "basaliob": 0.841, 
        "time": "2016-07-24T06:32:45.000Z", 
        "hightempinsulin": 1.55, 
        "bolussnooze": 0, 
        "iob": 0.841
      }, 
      {
        "netbasalinsulin": 1.2, 
        "activity": 0.0114, 
        "basaliob": 0.783, 
        "time": "2016-07-24T06:37:45.000Z", 
        "hightempinsulin": 1.55, 
        "bolussnooze": 0, 
        "iob": 0.783
      }, 
      {
        "netbasalinsulin": 1.2, 
        "activity": 0.0118, 
        "basaliob": 0.724, 
        "time": "2016-07-24T06:42:45.000Z", 
        "hightempinsulin": 1.55, 
        "bolussnooze": 0, 
        "iob": 0.724
      }, 
      {
        "netbasalinsulin": 1.1, 
        "activity": 0.012, 
        "basaliob": 0.664, 
        "time": "2016-07-24T06:47:45.000Z", 
        "hightempinsulin": 1.45, 
        "bolussnooze": 0, 
        "iob": 0.664
      }, 
      {
        "netbasalinsulin": 1.1, 
        "activity": 0.012, 
        "basaliob": 0.604, 
        "time": "2016-07-24T06:52:45.000Z", 
        "hightempinsulin": 1.45, 
        "bolussnooze": 0, 
        "iob": 0.604
      }, 
      {
        "netbasalinsulin": 1.15, 
        "activity": 0.0119, 
        "basaliob": 0.544, 
        "time": "2016-07-24T06:57:45.000Z", 
        "hightempinsulin": 1.45, 
        "bolussnooze": 0, 
        "iob": 0.544
      }, 
      {
        "netbasalinsulin": 1.15, 
        "activity": 0.0116, 
        "basaliob": 0.487, 
        "time": "2016-07-24T07:02:45.000Z", 
        "hightempinsulin": 1.45, 
        "bolussnooze": 0, 
        "iob": 0.487
      }, 
      {
        "netbasalinsulin": 1.2, 
        "activity": 0.011, 
        "basaliob": 0.431, 
        "time": "2016-07-24T07:07:45.000Z", 
        "hightempinsulin": 1.45, 
        "bolussnooze": 0, 
        "iob": 0.431
      }, 
      {
        "netbasalinsulin": 1.2, 
        "activity": 0.0104, 
        "basaliob": 0.38, 
        "time": "2016-07-24T07:12:45.000Z", 
        "hightempinsulin": 1.45, 
        "bolussnooze": 0, 
        "iob": 0.38
      }, 
      {
        "netbasalinsulin": 1.2, 
        "activity": 0.0097, 
        "basaliob": 0.331, 
        "time": "2016-07-24T07:17:45.000Z", 
        "hightempinsulin": 1.45, 
        "bolussnooze": 0, 
        "iob": 0.331
      }, 
      {
        "netbasalinsulin": 1.25, 
        "activity": 0.0091, 
        "basaliob": 0.285, 
        "time": "2016-07-24T07:22:45.000Z", 
        "hightempinsulin": 1.45, 
        "bolussnooze": 0, 
        "iob": 0.285
      }, 
      {
        "netbasalinsulin": 1.3, 
        "activity": 0.0084, 
        "basaliob": 0.243, 
        "time": "2016-07-24T07:27:45.000Z", 
        "hightempinsulin": 1.45, 
        "bolussnooze": 0, 
        "iob": 0.243
      }, 
      {
        "netbasalinsulin": 1.4, 
        "activity": 0.0077, 
        "basaliob": 0.205, 
        "time": "2016-07-24T07:32:45.000Z", 
        "hightempinsulin": 1.45, 
        "bolussnooze": 0, 
        "iob": 0.205
      }, 
      {
        "netbasalinsulin": 1.45, 
        "activity": 0.007, 
        "basaliob": 0.17, 
        "time": "2016-07-24T07:37:45.000Z", 
        "hightempinsulin": 1.45, 
        "bolussnooze": 0, 
        "iob": 0.17
      }, 
      {
        "netbasalinsulin": 1.45, 
        "activity": 0.0062, 
        "basaliob": 0.139, 
        "time": "2016-07-24T07:42:45.000Z", 
        "hightempinsulin": 1.45, 
        "bolussnooze": 0, 
        "iob": 0.139
      }, 
      {
        "netbasalinsulin": 1.4, 
        "activity": 0.0054, 
        "basaliob": 0.112, 
        "time": "2016-07-24T07:47:45.000Z", 
        "hightempinsulin": 1.4, 
        "bolussnooze": 0, 
        "iob": 0.112
      }, 
      {
        "netbasalinsulin": 1.35, 
        "activity": 0.0047, 
        "basaliob": 0.088, 
        "time": "2016-07-24T07:52:45.000Z", 
        "hightempinsulin": 1.35, 
        "bolussnooze": 0, 
        "iob": 0.088
      }, 
      {
        "netbasalinsulin": 1.25, 
        "activity": 0.004, 
        "basaliob": 0.068, 
        "time": "2016-07-24T07:57:45.000Z", 
        "hightempinsulin": 1.25, 
        "bolussnooze": 0, 
        "iob": 0.068
      }, 
      {
        "netbasalinsulin": 1.1, 
        "activity": 0.0034, 
        "basaliob": 0.052, 
        "time": "2016-07-24T08:02:45.000Z", 
        "hightempinsulin": 1.1, 
        "bolussnooze": 0, 
        "iob": 0.052
      }, 
      {
        "netbasalinsulin": 1, 
        "activity": 0.0028, 
        "basaliob": 0.037, 
        "time": "2016-07-24T08:07:45.000Z", 
        "hightempinsulin": 1, 
        "bolussnooze": 0, 
        "iob": 0.037
      }, 
      {
        "netbasalinsulin": 0.95, 
        "activity": 0.0023, 
        "basaliob": 0.026, 
        "time": "2016-07-24T08:12:45.000Z", 
        "hightempinsulin": 0.95, 
        "bolussnooze": 0, 
        "iob": 0.026
      }, 
      {
        "netbasalinsulin": 0.9, 
        "activity": 0.0018, 
        "basaliob": 0.017, 
        "time": "2016-07-24T08:17:45.000Z", 
        "hightempinsulin": 0.9, 
        "bolussnooze": 0, 
        "iob": 0.017
      }, 
      {
        "netbasalinsulin": 0.85, 
        "activity": 0.0013, 
        "basaliob": 0.01, 
        "time": "2016-07-24T08:22:45.000Z", 
        "hightempinsulin": 0.85, 
        "bolussnooze": 0, 
        "iob": 0.01
      }, 
      {
        "netbasalinsulin": 0.7, 
        "activity": 0.0009, 
        "basaliob": 0.006, 
        "time": "2016-07-24T08:27:45.000Z", 
        "hightempinsulin": 0.7, 
        "bolussnooze": 0, 
        "iob": 0.006
      }, 
      {
        "netbasalinsulin": 0.55, 
        "activity": 0.0006, 
        "basaliob": 0.003, 
        "time": "2016-07-24T08:32:45.000Z", 
        "hightempinsulin": 0.55, 
        "bolussnooze": 0, 
        "iob": 0.003
      }, 
      {
        "netbasalinsulin": 0.4, 
        "activity": 0.0003, 
        "basaliob": 0.001, 
        "time": "2016-07-24T08:37:45.000Z", 
        "hightempinsulin": 0.4, 
        "bolussnooze": 0, 
        "iob": 0.001
      }, 
      {
        "netbasalinsulin": 0.3, 
        "activity": 0.0001, 
        "basaliob": 0, 
        "time": "2016-07-24T08:42:45.000Z", 
        "hightempinsulin": 0.3, 
        "bolussnooze": 0, 
        "iob": 0
      }
    ], 
    "enacted": {
      "bg": 143, 
      "temp": "absolute", 
      "snoozeBG": 148, 
      "recieved": true, 
      "predBGs": {
        "COB": [
          143, 
          146, 
          149, 
          151, 
          154, 
          155, 
          157, 
          157, 
          158, 
          158, 
          157, 
          156, 
          155, 
          154, 
          153, 
          152, 
          151, 
          150, 
          149, 
          148, 
          148, 
          148, 
          148, 
          148, 
          148, 
          149, 
          150, 
          151, 
          153, 
          154, 
          156, 
          158, 
          160, 
          162, 
          164, 
          167, 
          169
        ], 
        "aCOB": [
          143, 
          150, 
          157, 
          164, 
          170, 
          176, 
          180, 
          184, 
          187, 
          190, 
          192, 
          194, 
          195, 
          196, 
          196, 
          196, 
          197, 
          197, 
          196, 
          196, 
          196, 
          196, 
          196, 
          196, 
          196, 
          197, 
          197, 
          197, 
          197, 
          197, 
          197, 
          197, 
          197, 
          196
        ], 
        "IOB": [
          143, 
          146, 
          148, 
          149, 
          150, 
          150, 
          149, 
          147, 
          145, 
          141, 
          137, 
          133, 
          128, 
          122, 
          117, 
          112, 
          106, 
          102, 
          97, 
          93, 
          89, 
          85, 
          81, 
          78, 
          76, 
          73, 
          71, 
          69, 
          68, 
          67, 
          66, 
          65, 
          64, 
          64, 
          63
        ]
      }, 
      "reason": "COB: 30, Dev: 32, BGI: -2.31, ISF: 88.9, Target: 80; Eventual BG 169 >= 80, temp 2.525<2.3U/hr", 
      "rate": 2.275, 
      "COB": 30, 
      "eventualBG": 169, 
      "timestamp": "2016-07-24T05:50:29.000Z", 
      "duration": 30, 
      "tick": "+3", 
      "IOB": 1.049
    }
  }, 
  "mmtune": {
    "scanDetails": [
      [
        "916.564", 
        5, 
        -95
      ], 
      [
        "916.588", 
        5, 
        -87
      ], 
      [
        "916.612", 
        5, 
        -85
      ], 
      [
        "916.636", 
        5, 
        -86
      ], 
      [
        "916.660", 
        5, 
        -86
      ], 
      [
        "916.684", 
        5, 
        -86
      ], 
      [
        "916.708", 
        5, 
        -90
      ]
    ], 
    "setFreq": 916.612, 
    "timestamp": "2016-07-24T05:47:41.000Z", 
    "usedDefault": false
  }
}