{
  "device": "openaps://indy-e1", 
  "pump": {
    "battery": {
      "status": "normal", 
      "voltage": 1.38
    }, 
    "status": {
      "status": "normal", 
      "timestamp": "2016-07-26T22:14:31.000Z", 
      "bolusing": false, 
      "suspended": false
    }, 
    "reservoir": 122.7, 
    "clock": "2016-07-26T15:14:16-07:00"
  }, 
  "uploader": {
    "battery": 58, 
    "batteryVoltage": 3760
  }, 
  "openaps": {
    "suggested": {
      "bg": 171, 
      "temp": "absolute", 
      "snoozeBG": 145, 
      "timestamp": "2016-07-26T22:16:26.000Z", 
      "predBGs": {
        "COB": [
          171, 
          173, 
          175, 
          176, 
          177, 
          178, 
          178, 
          178, 
          178, 
          178, 
          177, 
          176, 
          175, 
          174, 
          172, 
          169, 
          166, 
          163, 
          161, 
          158, 
          156, 
          154, 
          152, 
          150, 
          148, 
          147, 
          145, 
          144, 
          143, 
          143, 
          142, 
          141, 
          141, 
          141, 
          141, 
          140
        ], 
        "aCOB": [
          171, 
          174, 
          177, 
          179, 
          181, 
          182, 
          183, 
          183, 
          183, 
          182, 
          181, 
          180, 
          178, 
          175, 
          172, 
          169, 
          166, 
          163, 
          160, 
          157, 
          155, 
          153, 
          151, 
          149, 
          147, 
          146, 
          145, 
          144, 
          143, 
          142, 
          141, 
          141, 
          140, 
          140, 
          140, 
          140, 
          139
        ], 
        "IOB": [
          171, 
          173, 
          174, 
          175, 
          175, 
          175, 
          174, 
          173, 
          171, 
          169, 
          167, 
          164, 
          161, 
          158, 
          154, 
          151, 
          148, 
          145, 
          143, 
          140, 
          138, 
          135, 
          134, 
          132, 
          130, 
          129, 
          127, 
          126, 
          125, 
          125, 
          124, 
          123, 
          123, 
          123, 
          122
        ]
      }, 
      "rate": 1.85, 
      "reason": "COB: 16, Dev: 50, BGI: -5.95, ISF: 68.4, Target: 107; Eventual BG 145 >= 107, temp 1.55<1.85U/hr", 
      "COB": 16, 
      "eventualBG": 145, 
      "duration": 30, 
      "tick": "+6", 
      "IOB": 1.104
    }, 
    "iob": [
      {
        "netbasalinsulin": 1.45, 
        "activity": 0.0174, 
        "basaliob": 0.83, 
        "time": "2016-07-26T22:14:16.000Z", 
        "hightempinsulin": 1.45, 
        "bolussnooze": 0, 
        "iob": 1.104
      }, 
      {
        "netbasalinsulin": 1.5, 
        "activity": 0.0167, 
        "basaliob": 0.846, 
        "time": "2016-07-26T22:19:16.000Z", 
        "hightempinsulin": 1.5, 
        "bolussnooze": 0, 
        "iob": 1.07
      }, 
      {
        "netbasalinsulin": 1.6, 
        "activity": 0.0161, 
        "basaliob": 0.91, 
        "time": "2016-07-26T22:24:16.000Z", 
        "hightempinsulin": 1.6, 
        "bolussnooze": 0, 
        "iob": 1.09
      }, 
      {
        "netbasalinsulin": 1.6, 
        "activity": 0.0155, 
        "basaliob": 0.922, 
        "time": "2016-07-26T22:29:16.000Z", 
        "hightempinsulin": 1.6, 
        "bolussnooze": 0, 
        "iob": 1.062
      }, 
      {
        "netbasalinsulin": 1.6, 
        "activity": 0.0149, 
        "basaliob": 0.882, 
        "time": "2016-07-26T22:34:16.000Z", 
        "hightempinsulin": 1.6, 
        "bolussnooze": 0, 
        "iob": 0.988
      }, 
      {
        "netbasalinsulin": 1.55, 
        "activity": 0.0143, 
        "basaliob": 0.84, 
        "time": "2016-07-26T22:39:16.000Z", 
        "hightempinsulin": 1.55, 
        "bolussnooze": 0, 
        "iob": 0.916
      }, 
      {
        "netbasalinsulin": 1.5, 
        "activity": 0.0136, 
        "basaliob": 0.797, 
        "time": "2016-07-26T22:44:16.000Z", 
        "hightempinsulin": 1.5, 
        "bolussnooze": 0, 
        "iob": 0.848
      }, 
      {
        "netbasalinsulin": 1.5, 
        "activity": 0.0129, 
        "basaliob": 0.753, 
        "time": "2016-07-26T22:49:16.000Z", 
        "hightempinsulin": 1.5, 
        "bolussnooze": 0, 
        "iob": 0.784
      }, 
      {
        "netbasalinsulin": 1.45, 
        "activity": 0.0121, 
        "basaliob": 0.708, 
        "time": "2016-07-26T22:54:16.000Z", 
        "hightempinsulin": 1.45, 
        "bolussnooze": 0, 
        "iob": 0.724
      }, 
      {
        "netbasalinsulin": 1.35, 
        "activity": 0.0113, 
        "basaliob": 0.661, 
        "time": "2016-07-26T22:59:16.000Z", 
        "hightempinsulin": 1.35, 
        "bolussnooze": 0, 
        "iob": 0.667
      }, 
      {
        "netbasalinsulin": 1.2, 
        "activity": 0.0104, 
        "basaliob": 0.615, 
        "time": "2016-07-26T23:04:16.000Z", 
        "hightempinsulin": 1.2, 
        "bolussnooze": 0, 
        "iob": 0.615
      }, 
      {
        "netbasalinsulin": 1.15, 
        "activity": 0.0095, 
        "basaliob": 0.568, 
        "time": "2016-07-26T23:09:16.000Z", 
        "hightempinsulin": 1.15, 
        "bolussnooze": 0, 
        "iob": 0.568
      }, 
      {
        "netbasalinsulin": 1.1, 
        "activity": 0.0094, 
        "basaliob": 0.52, 
        "time": "2016-07-26T23:14:16.000Z", 
        "hightempinsulin": 1.1, 
        "bolussnooze": 0, 
        "iob": 0.52
      }, 
      {
        "netbasalinsulin": 1.1, 
        "activity": 0.0093, 
        "basaliob": 0.474, 
        "time": "2016-07-26T23:19:16.000Z", 
        "hightempinsulin": 1.1, 
        "bolussnooze": 0, 
        "iob": 0.474
      }, 
      {
        "netbasalinsulin": 1.1, 
        "activity": 0.0092, 
        "basaliob": 0.428, 
        "time": "2016-07-26T23:24:16.000Z", 
        "hightempinsulin": 1.1, 
        "bolussnooze": 0, 
        "iob": 0.428
      }, 
      {
        "netbasalinsulin": 1.1, 
        "activity": 0.0089, 
        "basaliob": 0.383, 
        "time": "2016-07-26T23:29:16.000Z", 
        "hightempinsulin": 1.1, 
        "bolussnooze": 0, 
        "iob": 0.383
      }, 
      {
        "netbasalinsulin": 1.1, 
        "activity": 0.0085, 
        "basaliob": 0.34, 
        "time": "2016-07-26T23:34:16.000Z", 
        "hightempinsulin": 1.1, 
        "bolussnooze": 0, 
        "iob": 0.34
      }, 
      {
        "netbasalinsulin": 1.1, 
        "activity": 0.0081, 
        "basaliob": 0.3, 
        "time": "2016-07-26T23:39:16.000Z", 
        "hightempinsulin": 1.1, 
        "bolussnooze": 0, 
        "iob": 0.3
      }, 
      {
        "netbasalinsulin": 1.1, 
        "activity": 0.0075, 
        "basaliob": 0.262, 
        "time": "2016-07-26T23:44:16.000Z", 
        "hightempinsulin": 1.1, 
        "bolussnooze": 0, 
        "iob": 0.262
      }, 
      {
        "netbasalinsulin": 1.1, 
        "activity": 0.0069, 
        "basaliob": 0.228, 
        "time": "2016-07-26T23:49:16.000Z", 
        "hightempinsulin": 1.1, 
        "bolussnooze": 0, 
        "iob": 0.228
      }, 
      {
        "netbasalinsulin": 1.05, 
        "activity": 0.0064, 
        "basaliob": 0.196, 
        "time": "2016-07-26T23:54:16.000Z", 
        "hightempinsulin": 1.05, 
        "bolussnooze": 0, 
        "iob": 0.196
      }, 
      {
        "netbasalinsulin": 1.05, 
        "activity": 0.0058, 
        "basaliob": 0.167, 
        "time": "2016-07-26T23:59:16.000Z", 
        "hightempinsulin": 1.05, 
        "bolussnooze": 0, 
        "iob": 0.167
      }, 
      {
        "netbasalinsulin": 1.05, 
        "activity": 0.0053, 
        "basaliob": 0.14, 
        "time": "2016-07-27T00:04:16.000Z", 
        "hightempinsulin": 1.05, 
        "bolussnooze": 0, 
        "iob": 0.14
      }, 
      {
        "netbasalinsulin": 1, 
        "activity": 0.0047, 
        "basaliob": 0.117, 
        "time": "2016-07-27T00:09:16.000Z", 
        "hightempinsulin": 1, 
        "bolussnooze": 0, 
        "iob": 0.117
      }, 
      {
        "netbasalinsulin": 0.95, 
        "activity": 0.0042, 
        "basaliob": 0.096, 
        "time": "2016-07-27T00:14:16.000Z", 
        "hightempinsulin": 0.95, 
        "bolussnooze": 0, 
        "iob": 0.096
      }, 
      {
        "netbasalinsulin": 0.95, 
        "activity": 0.0037, 
        "basaliob": 0.077, 
        "time": "2016-07-27T00:19:16.000Z", 
        "hightempinsulin": 0.95, 
        "bolussnooze": 0, 
        "iob": 0.077
      }, 
      {
        "netbasalinsulin": 0.9, 
        "activity": 0.0032, 
        "basaliob": 0.061, 
        "time": "2016-07-27T00:24:16.000Z", 
        "hightempinsulin": 0.9, 
        "bolussnooze": 0, 
        "iob": 0.061
      }, 
      {
        "netbasalinsulin": 0.85, 
        "activity": 0.0027, 
        "basaliob": 0.047, 
        "time": "2016-07-27T00:29:16.000Z", 
        "hightempinsulin": 0.85, 
        "bolussnooze": 0, 
        "iob": 0.047
      }, 
      {
        "netbasalinsulin": 0.8, 
        "activity": 0.0023, 
        "basaliob": 0.036, 
        "time": "2016-07-27T00:34:16.000Z", 
        "hightempinsulin": 0.8, 
        "bolussnooze": 0, 
        "iob": 0.036
      }, 
      {
        "netbasalinsulin": 0.75, 
        "activity": 0.0019, 
        "basaliob": 0.026, 
        "time": "2016-07-27T00:39:16.000Z", 
        "hightempinsulin": 0.75, 
        "bolussnooze": 0, 
        "iob": 0.026
      }, 
      {
        "netbasalinsulin": 0.65, 
        "activity": 0.0015, 
        "basaliob": 0.019, 
        "time": "2016-07-27T00:44:16.000Z", 
        "hightempinsulin": 0.65, 
        "bolussnooze": 0, 
        "iob": 0.019
      }, 
      {
        "netbasalinsulin": 0.6, 
        "activity": 0.0012, 
        "basaliob": 0.013, 
        "time": "2016-07-27T00:49:16.000Z", 
        "hightempinsulin": 0.6, 
        "bolussnooze": 0, 
        "iob": 0.013
      }, 
      {
        "netbasalinsulin": 0.5, 
        "activity": 0.0009, 
        "basaliob": 0.008, 
        "time": "2016-07-27T00:54:16.000Z", 
        "hightempinsulin": 0.5, 
        "bolussnooze": 0, 
        "iob": 0.008
      }, 
      {
        "netbasalinsulin": 0.45, 
        "activity": 0.0007, 
        "basaliob": 0.005, 
        "time": "2016-07-27T00:59:16.000Z", 
        "hightempinsulin": 0.45, 
        "bolussnooze": 0, 
        "iob": 0.005
      }, 
      {
        "netbasalinsulin": 0.35, 
        "activity": 0.0005, 
        "basaliob": 0.003, 
        "time": "2016-07-27T01:04:16.000Z", 
        "hightempinsulin": 0.35, 
        "bolussnooze": 0, 
        "iob": 0.003
      }, 
      {
        "netbasalinsulin": 0.3, 
        "activity": 0.0003, 
        "basaliob": 0.001, 
        "time": "2016-07-27T01:09:16.000Z", 
        "hightempinsulin": 0.3, 
        "bolussnooze": 0, 
        "iob": 0.001
      }
    ], 
    "enacted": {
      "bg": 171, 
      "temp": "absolute", 
      "snoozeBG": 145, 
      "recieved": true, 
      "predBGs": {
        "COB": [
          171, 
          173, 
          175, 
          176, 
          177, 
          178, 
          178, 
          178, 
          178, 
          178, 
          177, 
          176, 
          175, 
          174, 
          172, 
          169, 
          166, 
          163, 
          161, 
          158, 
          156, 
          154, 
          152, 
          150, 
          148, 
          147, 
          145, 
          144, 
          143, 
          143, 
          142, 
          141, 
          141, 
          141, 
          141, 
          140
        ], 
        "aCOB": [
          171, 
          174, 
          177, 
          179, 
          181, 
          182, 
          183, 
          183, 
          183, 
          182, 
          181, 
          180, 
          178, 
          175, 
          172, 
          169, 
          166, 
          163, 
          160, 
          157, 
          155, 
          153, 
          151, 
          149, 
          147, 
          146, 
          145, 
          144, 
          143, 
          142, 
          141, 
          141, 
          140, 
          140, 
          140, 
          140, 
          139
        ], 
        "IOB": [
          171, 
          173, 
          174, 
          175, 
          175, 
          175, 
          174, 
          173, 
          171, 
          169, 
          167, 
          164, 
          161, 
          158, 
          154, 
          151, 
          148, 
          145, 
          143, 
          140, 
          138, 
          135, 
          134, 
          132, 
          130, 
          129, 
          127, 
          126, 
          125, 
          125, 
          124, 
          123, 
          123, 
          123, 
          122
        ]
      }, 
      "reason": "COB: 16, Dev: 50, BGI: -5.95, ISF: 68.4, Target: 107; Eventual BG 145 >= 107, temp 1.55<1.85U/hr", 
      "rate": 1.85, 
      "COB": 16, 
      "eventualBG": 145, 
      "timestamp": "2016-07-26T22:16:47.000Z", 
      "duration": 30, 
      "tick": "+6", 
      "IOB": 1.104
    }
  }, 
  "mmtune": {
    "scanDetails": [
      [
        "916.564", 
        5, 
        -72
      ], 
      [
        "916.588", 
        5, 
        -66
      ], 
      [
        "916.612", 
        5, 
        -63
      ], 
      [
        "916.636", 
        3, 
        -78
      ], 
      [
        "916.660", 
        5, 
        -63
      ], 
      [
        "916.684", 
        5, 
        -63
      ], 
      [
        "916.708", 
        5, 
        -77
      ]
    ], 
    "setFreq": 916.684, 
    "timestamp": "2016-07-26T22:14:10.000Z", 
    "usedDefault": false
  }
}